Metadata-Version: 2.1
Name: guilded
Version: 0.0.4
Summary: A Python wrapper for the Guilded API
Home-page: UNKNOWN
Author: NotShin
License: MIT
Keywords: Guilded
Platform: UNKNOWN
Classifier: Development Status :: 1 - Planning
Classifier: Intended Audience :: Developers
Classifier: Natural Language :: English
Classifier: Operating System :: OS Independent
Classifier: License :: OSI Approved :: MIT License
Classifier: Programming Language :: Python :: 3
Classifier: Topic :: Software Development :: Libraries
Classifier: Topic :: Software Development :: Libraries :: Python Modules
Requires-Python: >=3.5.3
